regfile_generics/__init__.py
regfile_generics/regfile.py
regfile_generics/regfile_device.py
regfile_generics-0.1.0.dist-info/METADATA
regfile_generics-0.1.0.dist-info/WHEEL
regfile_generics-0.1.0.dist-info/licenses/LICENSE
regfile_generics-0.1.0.dist-info/RECORD
