Metadata-Version: 2.1
Name: regfile_generics
Version: 0.1.0
Summary: Python abstraction layer for registerfile access
Project-URL: Homepage, https://github.com/icglue/regfile_generics
Author-email: Felix Neumärker <felix.neumaerker@icglue.org>, Andreas Dixius <andreas.dixius@icglue.org>
Maintainer-email: Felix Neumärker <felix.neumaerker@icglue.org>, Andreas Dixius <andreas.dixius@icglue.org>
License-Expression: BSD-2-Clause
License-File: LICENSE
Keywords: registerfile
Classifier: Intended Audience :: Developers
Classifier: License :: OSI Approved :: BSD License
Classifier: Operating System :: OS Independent
Requires-Python: >=3.8
Provides-Extra: doc
Requires-Dist: sphinx; extra == 'doc'
Provides-Extra: test
Requires-Dist: pytest; extra == 'test'
